agentapps/__init__.py
agentapps/agent.py
agentapps/model.py
agentapps/tools.py
agentapps-0.1.1.dist-info/METADATA
agentapps-0.1.1.dist-info/WHEEL
agentapps-0.1.1.dist-info/top_level.txt
agentapps-0.1.1.dist-info/RECORD
