Metadata-Version: 2.4
Name: agentapps
Version: 0.1.1
Summary: AgenticAI - A flexible multi-agent orchestration framework with
Home-page: https://github.com/91abdul/agentapps
Author: 
Author-email: 
Project-URL: Bug Reports, https://github.com/91abdul/agentapps/issues
Project-URL: Source, https://github.com/91abdul/agentapps
Project-URL: Documentation, https://github.com/91abdul/agentapps#readme
Keywords: agents,ai,llm,orchestration,multi-agent,openai,web-search,gemini,grok
Classifier: Development Status :: 3 - Alpha
Classifier: Intended Audience :: Developers
Classifier: Topic :: Software Development :: Libraries :: Python Modules
Classifier: Programming Language :: Python :: 3
Classifier: Programming Language :: Python :: 3.8
Classifier: Programming Language :: Python :: 3.9
Classifier: Programming Language :: Python :: 3.10
Classifier: Programming Language :: Python :: 3.11
Classifier: Programming Language :: Python :: 3.12
Classifier: License :: OSI Approved :: MIT License
Classifier: Operating System :: OS Independent
Requires-Python: >=3.8
Requires-Dist: openai
Requires-Dist: google.genai
Requires-Dist: ddgs
Requires-Dist: beautifulsoup4
Requires-Dist: requests
Provides-Extra: dev
Requires-Dist: pytest; extra == "dev"
Requires-Dist: black; extra == "dev"
Requires-Dist: flake8; extra == "dev"
Requires-Dist: mypy; extra == "dev"
Dynamic: classifier
Dynamic: description
Dynamic: description-content-type
Dynamic: home-page
Dynamic: keywords
Dynamic: project-url
Dynamic: provides-extra
Dynamic: requires-dist
Dynamic: requires-python
Dynamic: summary
